tidesign/__about__.py
tidesign/__init__.py
tidesign-1.0.0rc1.dist-info/METADATA
tidesign-1.0.0rc1.dist-info/WHEEL
tidesign-1.0.0rc1.dist-info/top_level.txt
tidesign-1.0.0rc1.dist-info/RECORD
