Metadata-Version: 2.1
Name: tidesign
Version: 1.0.0rc1
Summary: Recipes for experimental designs
Author-email: Timothee Aubourg <timothee.aubourg@araymond.com>
License: Apache-2.0
Project-URL: Repository, https://github.com/quara-dev/tidesign
Project-URL: Issues, https://github.com/quara-dev/tidesign/issues
Project-URL: Project, https://github.com/orgs/quara-dev/projects/2
Classifier: Programming Language :: Python :: 3
Classifier: Programming Language :: Python :: Implementation :: CPython
Classifier: License :: OSI Approved :: Apache Software License
Classifier: Topic :: Scientific/Engineering
Classifier: Intended Audience :: Developers
Classifier: Intended Audience :: Science/Research
Classifier: Topic :: Scientific/Engineering :: Artificial Intelligence
Classifier: Topic :: Software Development
Requires-Python: <4.0,>=3.8
Provides-Extra: build
Requires-Dist: build ; extra == 'build'
Requires-Dist: invoke ; extra == 'build'
Requires-Dist: pip-tools ; extra == 'build'
Provides-Extra: dev
Requires-Dist: black ; extra == 'dev'
Requires-Dist: isort ; extra == 'dev'
Requires-Dist: invoke ; extra == 'dev'
Requires-Dist: flake8 ; extra == 'dev'
Requires-Dist: mypy ; extra == 'dev'
Requires-Dist: pytest ; extra == 'dev'
Requires-Dist: pytest-asyncio ; extra == 'dev'
Requires-Dist: pytest-cov ; extra == 'dev'
Requires-Dist: types-setuptools ; extra == 'dev'
Provides-Extra: docs
Requires-Dist: mkdocs-gen-files ; extra == 'docs'
Requires-Dist: mkdocs-literate-nav ; extra == 'docs'
Requires-Dist: mkdocs-material ; extra == 'docs'
Requires-Dist: mkdocs-section-index ; extra == 'docs'
Requires-Dist: mkdocstrings[python] ; extra == 'docs'
Requires-Dist: pymdown-extensions ; extra == 'docs'
